beasy/__init__.py
beasy/base.py
beasy/beasy.py
beasy/tables.py
beasy-1.0.0.dist-info/LICENSE
beasy-1.0.0.dist-info/METADATA
beasy-1.0.0.dist-info/WHEEL
beasy-1.0.0.dist-info/top_level.txt
beasy-1.0.0.dist-info/RECORD
