Metadata-Version: 2.1
Name: beasy
Version: 1.0.0
Summary: Simple Python API client for accessing data on the Bureau of Economic Analysis application programming interface.
Home-page: https://github.com/jdretz/simple-bea-client
Author: Jarrett Retz
Author-email: jretz@jrts.info
License: UNKNOWN
Project-URL: Bug Tracker, https://github.com/jdretz/simple-bea-client/issues
Platform: UNKNOWN
Classifier: Development Status :: 3 - Alpha
Classifier: License :: OSI Approved :: MIT License
Classifier: Programming Language :: Python :: 3
Classifier: Programming Language :: Python :: 3.6
Classifier: Programming Language :: Python :: 3.7
Classifier: Programming Language :: Python :: 3.8
Classifier: Programming Language :: Python :: 3.9
Classifier: Programming Language :: Python :: 3 :: Only
Requires-Python: >=3.6, <4
